{
  "frames": [
    {
      "filename": "powerup1.png",
      "frame": {
        "x": 0,
        "y": 0,
        "w": 66,
        "h": 78
      },
      "rotated": false,
      "trimmed": true,
      "spriteSourceSize": {
        "x": 15,
        "y": 9,
        "w": 66,
        "h": 78
      },
      "sourceSize": {
        "w": 96,
        "h": 96
      },
      "pivot": {
        "x": 0.5,
        "y": 0.5
      }
    },
    {
      "filename": "powerup15.png",
      "frame": {
        "x": 0,
        "y": 78,
        "w": 66,
        "h": 78
      },
      "rotated": false,
      "trimmed": true,
      "spriteSourceSize": {
        "x": 15,
        "y": 9,
        "w": 66,
        "h": 78
      },
      "sourceSize": {
        "w": 96,
        "h": 96
      },
      "pivot": {
        "x": 0.5,
        "y": 0.5
      }
    },
    {
      "filename": "powerup16.png",
      "frame": {
        "x": 0,
        "y": 156,
        "w": 33,
        "h": 75
      },
      "rotated": false,
      "trimmed": true,
      "spriteSourceSize": {
        "x": 24,
        "y": 6,
        "w": 33,
        "h": 75
      },
      "sourceSize": {
        "w": 96,
        "h": 96
      },
      "pivot": {
        "x": 0.5,
        "y": 0.5
      }
    },
    {
      "filename": "powerup12.png",
      "frame": {
        "x": 0,
        "y": 231,
        "w": 57,
        "h": 72
      },
      "rotated": false,
      "trimmed": true,
      "spriteSourceSize": {
        "x": 18,
        "y": 12,
        "w": 57,
        "h": 72
      },
      "sourceSize": {
        "w": 96,
        "h": 96
      },
      "pivot": {
        "x": 0.5,
        "y": 0.5
      }
    },
    {
      "filename": "powerup14.png",
      "frame": {
        "x": 33,
        "y": 156,
        "w": 57,
        "h": 72
      },
      "rotated": false,
      "trimmed": true,
      "spriteSourceSize": {
        "x": 18,
        "y": 12,
        "w": 57,
        "h": 72
      },
      "sourceSize": {
        "w": 96,
        "h": 96
      },
      "pivot": {
        "x": 0.5,
        "y": 0.5
      }
    },
    {
      "filename": "powerup13.png",
      "frame": {
        "x": 66,
        "y": 0,
        "w": 36,
        "h": 69
      },
      "rotated": false,
      "trimmed": true,
      "spriteSourceSize": {
        "x": 30,
        "y": 12,
        "w": 36,
        "h": 69
      },
      "sourceSize": {
        "w": 96,
        "h": 96
      },
      "pivot": {
        "x": 0.5,
        "y": 0.5
      }
    },
    {
      "filename": "powerup17.png",
      "frame": {
        "x": 0,
        "y": 231,
        "w": 57,
        "h": 72
      },
      "rotated": false,
      "trimmed": true,
      "spriteSourceSize": {
        "x": 18,
        "y": 12,
        "w": 57,
        "h": 72
      },
      "sourceSize": {
        "w": 96,
        "h": 96
      },
      "pivot": {
        "x": 0.5,
        "y": 0.5
      }
    }
  ],
  "meta": {
    "app": "http://free-tex-packer.com",
    "version": "0.6.7",
    "image": "texture.png",
    "format": "RGBA8888",
    "size": {
      "w": 102,
      "h": 303